lamb/__init__.py
lamb/lamb.py
lamb-0.0.1.post1.dist-info/LICENSE
lamb-0.0.1.post1.dist-info/METADATA
lamb-0.0.1.post1.dist-info/WHEEL
lamb-0.0.1.post1.dist-info/top_level.txt
lamb-0.0.1.post1.dist-info/RECORD
