Metadata-Version: 2.1
Name: lamb
Version: 0.0.1.post1
Summary: Express lambdas without `lamdbda`
Home-page: https://github.com/Nearoo/lamb
Author: Silas Gyger
Author-email: silasgyger@gmail.com
License: UNKNOWN
Platform: UNKNOWN
Classifier: Programming Language :: Python :: 3
Classifier: License :: OSI Approved :: MIT License
Classifier: Operating System :: OS Independent
Requires-Python: >=3.6
